paytechuz/__init__.py
paytechuz/factory.py
paytechuz/license.cpython-312-darwin.so
paytechuz/core/__init__.py
paytechuz/core/base.py
paytechuz/core/constants.py
paytechuz/core/dependencies.py
paytechuz/core/exceptions.py
paytechuz/core/http.py
paytechuz/core/utils.py
paytechuz/gateways/__init__.py
paytechuz/gateways/click/__init__.py
paytechuz/gateways/click/client.py
paytechuz/gateways/click/constants.py
paytechuz/gateways/click/internal.cpython-312-darwin.so
paytechuz/gateways/click/merchant.py
paytechuz/gateways/payme/__init__.py
paytechuz/gateways/payme/cards.py
paytechuz/gateways/payme/client.py
paytechuz/gateways/payme/constants.py
paytechuz/gateways/payme/internal.cpython-312-darwin.so
paytechuz/gateways/payme/receipts.py
paytechuz/gateways/paynet/__init__.py
paytechuz/gateways/paynet/client.py
paytechuz/gateways/paynet/constants.py
paytechuz/gateways/paynet/internal.cpython-312-darwin.so
paytechuz/gateways/uzum/__init__.py
paytechuz/gateways/uzum/client.py
paytechuz/gateways/uzum/constants.py
paytechuz/gateways/uzum/internal.cpython-312-darwin.so
paytechuz/integrations/__init__.py
paytechuz/integrations/django/__init__.py
paytechuz/integrations/django/admin.py
paytechuz/integrations/django/apps.py
paytechuz/integrations/django/models.py
paytechuz/integrations/django/signals.py
paytechuz/integrations/django/views.py
paytechuz/integrations/django/webhooks.py
paytechuz/integrations/django/internal_webhooks/__init__.py
paytechuz/integrations/django/internal_webhooks/click.cpython-312-darwin.so
paytechuz/integrations/django/internal_webhooks/payme.cpython-312-darwin.so
paytechuz/integrations/django/internal_webhooks/paynet.cpython-312-darwin.so
paytechuz/integrations/django/internal_webhooks/uzum.cpython-312-darwin.so
paytechuz/integrations/django/migrations/0001_initial.py
paytechuz/integrations/django/migrations/0002_alter_paymenttransaction_gateway.py
paytechuz/integrations/django/migrations/__init__.py
paytechuz/integrations/fastapi/__init__.py
paytechuz-0.3.44.dist-info/METADATA
paytechuz-0.3.44.dist-info/WHEEL
paytechuz-0.3.44.dist-info/top_level.txt
paytechuz-0.3.44.dist-info/RECORD
