Metadata-Version: 2.4
Name: paytechuz
Version: 0.3.44
Summary: Unified Python package for Uzbekistan payment gateways (Payme, Click, Uzum, Paynet)
Home-page: https://github.com/Muhammadali-Akbarov/paytechuz
Author: Muhammadali Akbarov
Author-email: Muhammadali Akbarov <muhammadali17abc@gmail.com>
License: MIT
Project-URL: Homepage, https://github.com/Muhammadali-Akbarov/paytechuz
Keywords: paytechuz,payme,click,uzum,paynet,uzbekistan,payment,gateway,payment-gateway,payment-processing,django,flask,fastapi
Classifier: Development Status :: 4 - Beta
Classifier: Intended Audience :: Developers
Classifier: Programming Language :: Python :: 3
Classifier: Programming Language :: Python :: 3.6
Classifier: Programming Language :: Python :: 3.7
Classifier: Programming Language :: Python :: 3.8
Classifier: Programming Language :: Python :: 3.9
Classifier: Programming Language :: Python :: 3.10
Classifier: Programming Language :: Python :: 3.11
Classifier: Programming Language :: Python :: 3.12
Classifier: License :: OSI Approved :: MIT License
Classifier: Operating System :: OS Independent
Classifier: Topic :: Software Development :: Libraries :: Python Modules
Requires-Python: >=3.6
Requires-Dist: requests<3.0,>=2.0
Requires-Dist: dataclasses<1.0,>=0.6; python_version < "3.7"
Requires-Dist: environs
Provides-Extra: django
Requires-Dist: django<6.0,>=3.0; extra == "django"
Provides-Extra: fastapi
Requires-Dist: fastapi<1.0.0,>=0.68.0; extra == "fastapi"
Requires-Dist: sqlalchemy<3.0,>=1.4; extra == "fastapi"
Requires-Dist: httpx<1.0,>=0.20; extra == "fastapi"
Requires-Dist: python-multipart==0.0.20; extra == "fastapi"
Requires-Dist: pydantic<2.0,>=1.8; extra == "fastapi"
Provides-Extra: flask
Requires-Dist: flask<3.0,>=2.0; extra == "flask"
Requires-Dist: flask-sqlalchemy<3.0,>=2.5; extra == "flask"
Dynamic: author
Dynamic: home-page
Dynamic: requires-python
